rgb2bgr/__init__.py
rgb2bgr-2.dist-info/METADATA
rgb2bgr-2.dist-info/WHEEL
rgb2bgr-2.dist-info/top_level.txt
rgb2bgr-2.dist-info/RECORD
