Metadata-Version: 2.1
Name: rgb2bgr
Version: 2
Summary: A rgb to bgr converter for python.
Home-page: UNKNOWN
Author: KironDevCoder
Author-email: mojanghouse@gmail.com
License: UNKNOWN
Project-URL: Documentation, https://rgb2bgr.readthedocs.io/en/latest/
Platform: UNKNOWN
Classifier: Programming Language :: Python :: 3
Classifier: License :: OSI Approved :: MIT License
Classifier: Operating System :: OS Independent
